paymongo/__init__.py
paymongo/constants.py
paymongo/hook.py
paymongo/payment.py
paymongo/payment_intent.py
paymongo/payment_method.py
paymongo/paymongo.py
paymongo/source.py
paymongo/urls.py
paymongo/web_hook.py
paymongo-0.1.3.dev0.dist-info/LICENSE.txt
paymongo-0.1.3.dev0.dist-info/METADATA
paymongo-0.1.3.dev0.dist-info/WHEEL
paymongo-0.1.3.dev0.dist-info/top_level.txt
paymongo-0.1.3.dev0.dist-info/RECORD
