Metadata-Version: 2.1
Name: paymongo
Version: 0.1.3.dev0
Summary: Python package for Paymongo API
Home-page: https://github.com/bailabs/paymongo
Author: Chris Ian Fiel
Author-email: ccfiel@bai.ph
License: UNKNOWN
Platform: UNKNOWN
Classifier: Programming Language :: Python :: 3
Classifier: License :: OSI Approved :: MIT License
Classifier: Operating System :: OS Independent
Requires-Python: >=3.6
